{
  "Cotacoes": {
    "BTC": 313050.25,
    "ETH": 15030.11,
    "XRP": 2.6
  },
  "12345678910": {
    "Nome": "Breno",
    "CPF": "12345678910",
    "Senha": "123456",
    "Reais": 680688.745,
    "Bitcoin": 1.0,
    "Ethereum": 0.0,
    "Ripple": 0.0,
    "Extratos": [
      {
        "Data": "26-03-2025 11:23",
        "+/-": "+",
        "Valor": 1000000.0,
        "Tipo": "REAL",
        "CT": 0.0,
        "TX": 0.0,
        "REAL": 1000000.0,
        "BTC": 0.0,
        "ETH": 0.0,
        "XRP": 0.0
      },
      {
        "Data": "26-03-2025 11:23",
        "+/-": "+",
        "Valor": 1.0,
        "Tipo": "BTC",
        "CT": 313050.25,
        "TX": 0.02,
        "REAL": 680688.745,
        "BTC": 1.0,
        "ETH": 0.0,
        "XRP": 0.0
      }
    ]
  }
}